local_components/__init__.py
local_components/containers.py
local_components/headers.py
streamlit_shadcn_ui/__init__.py
streamlit_shadcn_ui/components/packages/frontend/dist/index.html
streamlit_shadcn_ui/components/packages/frontend/dist/assets/index--vB49rLl.js
streamlit_shadcn_ui/components/packages/frontend/dist/assets/index-bVWeJWwc.css
streamlit_shadcn_ui/py_components/__init__.py
streamlit_shadcn_ui/py_components/alert_dialog.py
streamlit_shadcn_ui/py_components/avatar.py
streamlit_shadcn_ui/py_components/badges.py
streamlit_shadcn_ui/py_components/button.py
streamlit_shadcn_ui/py_components/card.py
streamlit_shadcn_ui/py_components/checkbox.py
streamlit_shadcn_ui/py_components/date_picker.py
streamlit_shadcn_ui/py_components/hover_card.py
streamlit_shadcn_ui/py_components/input.py
streamlit_shadcn_ui/py_components/link_button.py
streamlit_shadcn_ui/py_components/metric_card.py
streamlit_shadcn_ui/py_components/radio_group.py
streamlit_shadcn_ui/py_components/select.py
streamlit_shadcn_ui/py_components/slider.py
streamlit_shadcn_ui/py_components/switch.py
streamlit_shadcn_ui/py_components/table.py
streamlit_shadcn_ui/py_components/tabs.py
streamlit_shadcn_ui/py_components/textarea.py
streamlit_shadcn_ui/py_components/base/__init__.py
streamlit_shadcn_ui/py_components/base/context.py
streamlit_shadcn_ui/py_components/base/element.py
streamlit_shadcn_ui/py_components/containers/__init__.py
streamlit_shadcn_ui/py_components/utils/__init__.py
streamlit_shadcn_ui/py_components/utils/callback.py
streamlit_shadcn_ui/py_components/utils/declare.py
streamlit_shadcn_ui/py_components/utils/session.py
streamlit_shadcn_ui-0.1.18.dist-info/LICENSE
streamlit_shadcn_ui-0.1.18.dist-info/METADATA
streamlit_shadcn_ui-0.1.18.dist-info/WHEEL
streamlit_shadcn_ui-0.1.18.dist-info/top_level.txt
streamlit_shadcn_ui-0.1.18.dist-info/RECORD
