Metadata-Version: 2.1
Name: streamlit-shadcn-ui
Version: 0.1.18
Summary: Using shadcn components in Streamlit
Home-page: https://github.com/ObservedObserver/streamlit-shadcn-ui
Author: Observed Observer
Author-email: Observed Observer <ooer@kanaries.net>
License: MIT License
Project-URL: homepage, https://github.com/ObservedObserver/streamlit-shadcn-ui
Project-URL: repository, https://github.com/ObservedObserver/streamlit-shadcn-ui
Keywords: streamlit,shadcn,ui,components
Classifier: Programming Language :: Python :: 3
Classifier: License :: OSI Approved :: MIT License
Classifier: Operating System :: OS Independent
Requires-Python: >=3.7
License-File: LICENSE
Requires-Dist: streamlit
Requires-Dist: streamlit_extras
Requires-Dist: pandas
